jupyterlab_double_sharp/__init__.py
jupyterlab_double_sharp/_version.py
jupyterlab_double_sharp-0.1.1.data/data/share/jupyter/labextensions/jupyterlab-double-sharp/package.json
jupyterlab_double_sharp-0.1.1.data/data/share/jupyter/labextensions/jupyterlab-double-sharp/schemas/jupyterlab-double-sharp/package.json.orig
jupyterlab_double_sharp-0.1.1.data/data/share/jupyter/labextensions/jupyterlab-double-sharp/schemas/jupyterlab-double-sharp/plugin.json
jupyterlab_double_sharp-0.1.1.data/data/share/jupyter/labextensions/jupyterlab-double-sharp/static/17.669243992b6918db1a02.js
jupyterlab_double_sharp-0.1.1.data/data/share/jupyter/labextensions/jupyterlab-double-sharp/static/182.949d27308e2be71cf257.js
jupyterlab_double_sharp-0.1.1.data/data/share/jupyter/labextensions/jupyterlab-double-sharp/static/187.e1fb0142769a8b6e9f54.js
jupyterlab_double_sharp-0.1.1.data/data/share/jupyter/labextensions/jupyterlab-double-sharp/static/485.575bb303bf5cae8fc426.js
jupyterlab_double_sharp-0.1.1.data/data/share/jupyter/labextensions/jupyterlab-double-sharp/static/485.575bb303bf5cae8fc426.js.LICENSE.txt
jupyterlab_double_sharp-0.1.1.data/data/share/jupyter/labextensions/jupyterlab-double-sharp/static/505.6b8d9d6c2a9dae6e9ca5.js
jupyterlab_double_sharp-0.1.1.data/data/share/jupyter/labextensions/jupyterlab-double-sharp/static/800.cc999f00b421765095ae.js
jupyterlab_double_sharp-0.1.1.data/data/share/jupyter/labextensions/jupyterlab-double-sharp/static/82.5ca86452b501114b609d.js
jupyterlab_double_sharp-0.1.1.data/data/share/jupyter/labextensions/jupyterlab-double-sharp/static/886.dbc8b31bb1a213ea9838.js
jupyterlab_double_sharp-0.1.1.data/data/share/jupyter/labextensions/jupyterlab-double-sharp/static/924.f1d1fb44878fc1a80473.js
jupyterlab_double_sharp-0.1.1.data/data/share/jupyter/labextensions/jupyterlab-double-sharp/static/remoteEntry.e1b8a9ca012e12bf6cd0.js
jupyterlab_double_sharp-0.1.1.data/data/share/jupyter/labextensions/jupyterlab-double-sharp/static/style.js
jupyterlab_double_sharp-0.1.1.dist-info/METADATA
jupyterlab_double_sharp-0.1.1.dist-info/WHEEL
jupyterlab_double_sharp-0.1.1.dist-info/licenses/LICENSE
jupyterlab_double_sharp-0.1.1.dist-info/RECORD
