Metadata-Version: 2.3
Name: jupyterlab_double_sharp
Version: 0.1.1
Dynamic: Keywords
Summary: Jupyterlab extension that provides features like execution cache, auto-dependency, external file loading(TODO) and more.
Project-URL: Homepage, https://github.com/freeislet/jupyterlab-double-sharp
Project-URL: Bug Tracker, https://github.com/freeislet/jupyterlab-double-sharp/issues
Project-URL: Repository, https://github.com/freeislet/jupyterlab-double-sharp.git
Author-email: Sunghwan Kang <freeislet@gmail.com>
License: BSD 3-Clause License
License-File: LICENSE
Classifier: Framework :: Jupyter
Classifier: Framework :: Jupyter :: JupyterLab
Classifier: Framework :: Jupyter :: JupyterLab :: 4
Classifier: Framework :: Jupyter :: JupyterLab :: Extensions
Classifier: Framework :: Jupyter :: JupyterLab :: Extensions :: Prebuilt
Classifier: License :: OSI Approved :: BSD License
Classifier: Programming Language :: Python
Classifier: Programming Language :: Python :: 3
Classifier: Programming Language :: Python :: 3.8
Classifier: Programming Language :: Python :: 3.9
Classifier: Programming Language :: Python :: 3.10
Classifier: Programming Language :: Python :: 3.11
Classifier: Programming Language :: Python :: 3.12
Requires-Python: >=3.8
